[
  {
    "model": "auth.group",
    "fields": {
      "name": "ZBM",
      "permissions": [
        ["view_ward", "cms", "ward"],
        ["add_ward", "cms", "ward"],
        ["change_ward", "cms", "ward"]
      ]
    }
  },
  {
    "model": "auth.group",
    "fields": {
      "name": "STATION_MANAGEMENT",
      "permissions": [
        ["view_patient", "cms", "patient"],
        ["add_patient", "cms", "patient"],
        ["change_ward", "cms", "ward"]
      ]
    }
  },
  {
    "model": "auth.group",
    "fields": {
      "name": "MEDICAL_PERSONNEL",
      "permissions": [
        ["view_patient", "cms", "patient"],
        ["change_patient", "cms", "patient"]
      ]
    }
  }
]
